{"tblStudentAchva": [
    {
        "studentId": 316315332,
        "lessonId": 27473,
        "eventCode": 2,
        "justified": -1,
        "reporterid": 17682006,
        "groupid": 11193003,
        "lesson": 3,
        "lessondate": "2014-01-09T00:00:00",
        "name": "העדרות",
        "justification": "ללא הערות",
        "teacherName": "שורק פיטר",
        "subjectName": "אנגלית MODULE F",
        "remarktext": ""
    },
    {
        "studentId": 316315332,
        "lessonId": 26440,
        "eventCode": 2,
        "justified": -1,
        "reporterid": 24621054,
        "groupid": 11011008,
        "lesson": 3,
        "lessondate": "2014-01-06T00:00:00",
        "name": "העדרות",
        "justification": "ללא הערות",
        "teacherName": "פרידמן דורית",
        "subjectName": "ספרות",
        "remarktext": ""
    },
    {
        "studentId": 316315332,
        "lessonId": 21825,
        "eventCode": 2,
        "justified": -1,
        "reporterid": 37507167,
        "groupid": 11018006,
        "lesson": 3,
        "lessondate": "2013-12-17T00:00:00",
        "name": "העדרות",
        "justification": "ללא הערות",
        "teacherName": "מגל אילנית",
        "subjectName": "אזרחות",
        "remarktext": ""
    },
    {
        "studentId": 316315332,
        "lessonId": 22126,
        "eventCode": 2,
        "justified": -1,
        "reporterid": 57311813,
        "groupid": 11136003,
        "lesson": 4,
        "lessondate": "2013-12-17T00:00:00",
        "name": "העדרות",
        "justification": "ללא הערות",
        "teacherName": "חלפון חגית",
        "subjectName": "חינוך",
        "remarktext": ""
    },
    {
        "studentId": 316315332,
        "lessonId": 20026,
        "eventCode": 2,
        "justified": -1,
        "reporterid": 17682006,
        "groupid": 11193003,
        "lesson": 6,
        "lessondate": "2013-12-09T00:00:00",
        "name": "העדרות",
        "justification": "ללא הערות",
        "teacherName": "שורק פיטר",
        "subjectName": "אנגלית MODULE F",
        "remarktext": ""
    },
    {
        "studentId": 316315332,
        "lessonId": 20027,
        "eventCode": 2,
        "justified": -1,
        "reporterid": 17682006,
        "groupid": 11193003,
        "lesson": 7,
        "lessondate": "2013-12-09T00:00:00",
        "name": "העדרות",
        "justification": "ללא הערות",
        "teacherName": "שורק פיטר",
        "subjectName": "אנגלית MODULE F",
        "remarktext": ""
    },
    {
        "studentId": 316315332,
        "lessonId": 19773,
        "eventCode": 2,
        "justified": -1,
        "reporterid": 57381683,
        "groupid": 11011008,
        "lesson": 3,
        "lessondate": "2013-12-09T00:00:00",
        "name": "העדרות",
        "justification": "ללא הערות",
        "teacherName": "שקד ענת",
        "subjectName": "מילוי מקום",
        "remarktext": ""
    },
    {
        "studentId": 316315332,
        "lessonId": 17143,
        "eventCode": 2,
        "justified": -1,
        "reporterid": 55379952,
        "groupid": 11010001,
        "lesson": 1,
        "lessondate": "2013-11-20T00:00:00",
        "name": "העדרות",
        "justification": "ללא הערות",
        "teacherName": "ברקאי עפרה",
        "subjectName": "תנך",
        "remarktext": ""
    },
    {
        "studentId": 316315332,
        "lessonId": 17363,
        "eventCode": 2,
        "justified": -1,
        "reporterid": 37507167,
        "groupid": 11018006,
        "lesson": 4,
        "lessondate": "2013-11-20T00:00:00",
        "name": "העדרות",
        "justification": "ללא הערות",
        "teacherName": "מגל אילנית",
        "subjectName": "אזרחות",
        "remarktext": ""
    },
    {
        "studentId": 316315332,
        "lessonId": 17235,
        "eventCode": 2,
        "justified": -1,
        "reporterid": 17682006,
        "groupid": 11193003,
        "lesson": 2,
        "lessondate": "2013-11-20T00:00:00",
        "name": "העדרות",
        "justification": "ללא הערות",
        "teacherName": "שורק פיטר",
        "subjectName": "אנגלית MODULE F",
        "remarktext": ""
    },
    {
        "studentId": 316315332,
        "lessonId": 16327,
        "eventCode": 2,
        "justified": -1,
        "reporterid": 22419683,
        "groupid": 11019004,
        "lesson": 3,
        "lessondate": "2013-11-17T00:00:00",
        "name": "העדרות",
        "justification": "ללא הערות",
        "teacherName": "ברק דובי",
        "subjectName": "חינוך גופני",
        "remarktext": ""
    },
    {
        "studentId": 316315332,
        "lessonId": 16328,
        "eventCode": 2,
        "justified": -1,
        "reporterid": 22419683,
        "groupid": 11019004,
        "lesson": 4,
        "lessondate": "2013-11-17T00:00:00",
        "name": "העדרות",
        "justification": "ללא הערות",
        "teacherName": "ברק דובי",
        "subjectName": "חינוך גופני",
        "remarktext": ""
    },
    {
        "studentId": 316315332,
        "lessonId": 10395,
        "eventCode": 2,
        "justified": -1,
        "reporterid": 17682006,
        "groupid": 11193003,
        "lesson": 1,
        "lessondate": "2013-10-25T00:00:00",
        "name": "העדרות",
        "justification": "ללא הערות",
        "teacherName": "שורק פיטר",
        "subjectName": "אנגלית MODULE F",
        "remarktext": ""
    },
    {
        "studentId": 316315332,
        "lessonId": 10048,
        "eventCode": 7,
        "justified": -1,
        "reporterid": 58312042,
        "groupid": 11052001,
        "lesson": 5,
        "lessondate": "2013-10-23T00:00:00",
        "name": "הפרעה",
        "justification": "ללא הערות",
        "teacherName": "סלומון מרדכי",
        "subjectName": "פיסיקה",
        "remarktext": ""
    },
    {
        "studentId": 316315332,
        "lessonId": 8758,
        "eventCode": 2,
        "justified": -1,
        "reporterid": 17682006,
        "groupid": 11193003,
        "lesson": 1,
        "lessondate": "2013-10-18T00:00:00",
        "name": "העדרות",
        "justification": "ללא הערות",
        "teacherName": "שורק פיטר",
        "subjectName": "אנגלית MODULE F",
        "remarktext": ""
    },
    {
        "studentId": 316315332,
        "lessonId": 8179,
        "eventCode": 29,
        "justified": -1,
        "reporterid": 58312042,
        "groupid": 11052001,
        "lesson": 6,
        "lessondate": "2013-10-16T00:00:00",
        "name": "חיזוק חיובי",
        "justification": "ללא הערות",
        "teacherName": "סלומון מרדכי",
        "subjectName": "פיסיקה",
        "remarktext": ""
    },
    {
        "studentId": 316315332,
        "lessonId": 8178,
        "eventCode": 29,
        "justified": -1,
        "reporterid": 58312042,
        "groupid": 11052001,
        "lesson": 5,
        "lessondate": "2013-10-16T00:00:00",
        "name": "חיזוק חיובי",
        "justification": "ללא הערות",
        "teacherName": "סלומון מרדכי",
        "subjectName": "פיסיקה",
        "remarktext": ""
    },
    {
        "studentId": 316315332,
        "lessonId": 6644,
        "eventCode": 2,
        "justified": 1,
        "reporterid": 17682006,
        "groupid": 11193003,
        "lesson": 1,
        "lessondate": "2013-10-11T00:00:00",
        "name": "העדרות",
        "justification": "אישור רפואי",
        "teacherName": "שורק פיטר",
        "subjectName": "אנגלית MODULE F",
        "remarktext": ""
    },
    {
        "studentId": 316315332,
        "lessonId": 7502,
        "eventCode": 2,
        "justified": 1,
        "reporterid": 37507167,
        "groupid": 11018006,
        "lesson": 2,
        "lessondate": "2013-10-11T00:00:00",
        "name": "העדרות",
        "justification": "אישור רפואי",
        "teacherName": "מגל אילנית",
        "subjectName": "אזרחות",
        "remarktext": ""
    },
    {
        "studentId": 316315332,
        "lessonId": 6434,
        "eventCode": 2,
        "justified": 1,
        "reporterid": 58312042,
        "groupid": 11052001,
        "lesson": 1,
        "lessondate": "2013-10-10T00:00:00",
        "name": "העדרות",
        "justification": "אישור רפואי",
        "teacherName": "סלומון מרדכי",
        "subjectName": "פיסיקה",
        "remarktext": ""
    },
    {
        "studentId": 316315332,
        "lessonId": 6433,
        "eventCode": 2,
        "justified": 1,
        "reporterid": 55379952,
        "groupid": 11010001,
        "lesson": 4,
        "lessondate": "2013-10-10T00:00:00",
        "name": "העדרות",
        "justification": "אישור רפואי",
        "teacherName": "ברקאי עפרה",
        "subjectName": "תנך",
        "remarktext": ""
    },
    {
        "studentId": 316315332,
        "lessonId": 6435,
        "eventCode": 2,
        "justified": 1,
        "reporterid": 58312042,
        "groupid": 11052001,
        "lesson": 2,
        "lessondate": "2013-10-10T00:00:00",
        "name": "העדרות",
        "justification": "אישור רפואי",
        "teacherName": "סלומון מרדכי",
        "subjectName": "פיסיקה",
        "remarktext": ""
    },
    {
        "studentId": 316315332,
        "lessonId": 6650,
        "eventCode": 2,
        "justified": 1,
        "reporterid": 17682006,
        "groupid": 11193003,
        "lesson": 3,
        "lessondate": "2013-10-10T00:00:00",
        "name": "העדרות",
        "justification": "אישור רפואי",
        "teacherName": "שורק פיטר",
        "subjectName": "אנגלית MODULE F",
        "remarktext": ""
    },
    {
        "studentId": 316315332,
        "lessonId": 6410,
        "eventCode": 2,
        "justified": 1,
        "reporterid": 40762528,
        "groupid": 11028005,
        "lesson": 5,
        "lessondate": "2013-10-10T00:00:00",
        "name": "העדרות",
        "justification": "אישור רפואי",
        "teacherName": "שרף מירב",
        "subjectName": "עברית",
        "remarktext": ""
    },
    {
        "studentId": 316315332,
        "lessonId": 6429,
        "eventCode": 2,
        "justified": 1,
        "reporterid": 58312042,
        "groupid": 11052001,
        "lesson": 6,
        "lessondate": "2013-10-09T00:00:00",
        "name": "העדרות",
        "justification": "אישור רפואי",
        "teacherName": "סלומון מרדכי",
        "subjectName": "פיסיקה",
        "remarktext": ""
    },
    {
        "studentId": 316315332,
        "lessonId": 7497,
        "eventCode": 2,
        "justified": 1,
        "reporterid": 37507167,
        "groupid": 11018006,
        "lesson": 4,
        "lessondate": "2013-10-09T00:00:00",
        "name": "העדרות",
        "justification": "אישור רפואי",
        "teacherName": "מגל אילנית",
        "subjectName": "אזרחות",
        "remarktext": ""
    },
    {
        "studentId": 316315332,
        "lessonId": 6340,
        "eventCode": 2,
        "justified": 1,
        "reporterid": 17682006,
        "groupid": 11193003,
        "lesson": 2,
        "lessondate": "2013-10-09T00:00:00",
        "name": "העדרות",
        "justification": "אישור רפואי",
        "teacherName": "שורק פיטר",
        "subjectName": "אנגלית MODULE F",
        "remarktext": ""
    },
    {
        "studentId": 316315332,
        "lessonId": 6428,
        "eventCode": 2,
        "justified": 1,
        "reporterid": 58312042,
        "groupid": 11052001,
        "lesson": 5,
        "lessondate": "2013-10-09T00:00:00",
        "name": "העדרות",
        "justification": "אישור רפואי",
        "teacherName": "סלומון מרדכי",
        "subjectName": "פיסיקה",
        "remarktext": ""
    },
    {
        "studentId": 316315332,
        "lessonId": 6096,
        "eventCode": 2,
        "justified": 1,
        "reporterid": 55379952,
        "groupid": 11010001,
        "lesson": 1,
        "lessondate": "2013-10-09T00:00:00",
        "name": "העדרות",
        "justification": "אישור רפואי",
        "teacherName": "ברקאי עפרה",
        "subjectName": "תנך",
        "remarktext": ""
    },
    {
        "studentId": 316315332,
        "lessonId": 4043,
        "eventCode": 29,
        "justified": -1,
        "reporterid": 37507167,
        "groupid": 11018006,
        "lesson": 5,
        "lessondate": "2013-09-30T00:00:00",
        "name": "חיזוק חיובי",
        "justification": "ללא הערות",
        "teacherName": "מגל אילנית",
        "subjectName": "אזרחות",
        "remarktext": ""
    },
    {
        "studentId": 316315332,
        "lessonId": 3176,
        "eventCode": 2,
        "justified": 15,
        "reporterid": 58312042,
        "groupid": 11052001,
        "lesson": 1,
        "lessondate": "2013-09-12T00:00:00",
        "name": "העדרות",
        "justification": "לימודים באוניברסיטה",
        "teacherName": "סלומון מרדכי",
        "subjectName": "פיסיקה",
        "remarktext": ""
    },
    {
        "studentId": 316315332,
        "lessonId": 3239,
        "eventCode": 2,
        "justified": 15,
        "reporterid": 55379952,
        "groupid": 11010001,
        "lesson": 4,
        "lessondate": "2013-09-12T00:00:00",
        "name": "העדרות",
        "justification": "לימודים באוניברסיטה",
        "teacherName": "ברקאי עפרה",
        "subjectName": "תנך",
        "remarktext": ""
    },
    {
        "studentId": 316315332,
        "lessonId": 3177,
        "eventCode": 2,
        "justified": 15,
        "reporterid": 58312042,
        "groupid": 11052001,
        "lesson": 2,
        "lessondate": "2013-09-12T00:00:00",
        "name": "העדרות",
        "justification": "לימודים באוניברסיטה",
        "teacherName": "סלומון מרדכי",
        "subjectName": "פיסיקה",
        "remarktext": ""
    },
    {
        "studentId": 316315332,
        "lessonId": 3245,
        "eventCode": 2,
        "justified": 15,
        "reporterid": 17682006,
        "groupid": 11193003,
        "lesson": 3,
        "lessondate": "2013-09-12T00:00:00",
        "name": "העדרות",
        "justification": "לימודים באוניברסיטה",
        "teacherName": "שורק פיטר",
        "subjectName": "אנגלית MODULE F",
        "remarktext": ""
    },
    {
        "studentId": 316315332,
        "lessonId": 3170,
        "eventCode": 2,
        "justified": 15,
        "reporterid": 58312042,
        "groupid": 11052001,
        "lesson": 6,
        "lessondate": "2013-09-11T00:00:00",
        "name": "העדרות",
        "justification": "לימודים באוניברסיטה",
        "teacherName": "סלומון מרדכי",
        "subjectName": "פיסיקה",
        "remarktext": ""
    },
    {
        "studentId": 316315332,
        "lessonId": 3252,
        "eventCode": 2,
        "justified": 15,
        "reporterid": 17682006,
        "groupid": 11193003,
        "lesson": 2,
        "lessondate": "2013-09-11T00:00:00",
        "name": "העדרות",
        "justification": "לימודים באוניברסיטה",
        "teacherName": "שורק פיטר",
        "subjectName": "אנגלית MODULE F",
        "remarktext": ""
    },
    {
        "studentId": 316315332,
        "lessonId": 3017,
        "eventCode": 2,
        "justified": 15,
        "reporterid": 37507167,
        "groupid": 11018006,
        "lesson": 4,
        "lessondate": "2013-09-11T00:00:00",
        "name": "העדרות",
        "justification": "לימודים באוניברסיטה",
        "teacherName": "מגל אילנית",
        "subjectName": "אזרחות",
        "remarktext": ""
    },
    {
        "studentId": 316315332,
        "lessonId": 3171,
        "eventCode": 2,
        "justified": 15,
        "reporterid": 58312042,
        "groupid": 11052001,
        "lesson": 5,
        "lessondate": "2013-09-11T00:00:00",
        "name": "העדרות",
        "justification": "לימודים באוניברסיטה",
        "teacherName": "סלומון מרדכי",
        "subjectName": "פיסיקה",
        "remarktext": ""
    },
    {
        "studentId": 316315332,
        "lessonId": 2333,
        "eventCode": 2,
        "justified": 15,
        "reporterid": 58312042,
        "groupid": 11052001,
        "lesson": 2,
        "lessondate": "2013-09-09T00:00:00",
        "name": "העדרות",
        "justification": "לימודים באוניברסיטה",
        "teacherName": "סלומון מרדכי",
        "subjectName": "פיסיקה",
        "remarktext": ""
    },
    {
        "studentId": 316315332,
        "lessonId": 2498,
        "eventCode": 2,
        "justified": 15,
        "reporterid": 17682006,
        "groupid": 11193003,
        "lesson": 6,
        "lessondate": "2013-09-09T00:00:00",
        "name": "העדרות",
        "justification": "לימודים באוניברסיטה",
        "teacherName": "שורק פיטר",
        "subjectName": "אנגלית MODULE F",
        "remarktext": ""
    },
    {
        "studentId": 316315332,
        "lessonId": 2997,
        "eventCode": 2,
        "justified": 15,
        "reporterid": 37507167,
        "groupid": 11018006,
        "lesson": 5,
        "lessondate": "2013-09-09T00:00:00",
        "name": "העדרות",
        "justification": "לימודים באוניברסיטה",
        "teacherName": "מגל אילנית",
        "subjectName": "אזרחות",
        "remarktext": ""
    },
    {
        "studentId": 316315332,
        "lessonId": 2332,
        "eventCode": 2,
        "justified": 15,
        "reporterid": 58312042,
        "groupid": 11052001,
        "lesson": 1,
        "lessondate": "2013-09-09T00:00:00",
        "name": "העדרות",
        "justification": "לימודים באוניברסיטה",
        "teacherName": "סלומון מרדכי",
        "subjectName": "פיסיקה",
        "remarktext": ""
    },
    {
        "studentId": 316315332,
        "lessonId": 2341,
        "eventCode": 2,
        "justified": 15,
        "reporterid": 24621054,
        "groupid": 11011008,
        "lesson": 3,
        "lessondate": "2013-09-09T00:00:00",
        "name": "העדרות",
        "justification": "לימודים באוניברסיטה",
        "teacherName": "פרידמן דורית",
        "subjectName": "ספרות",
        "remarktext": ""
    },
    {
        "studentId": 316315332,
        "lessonId": 2499,
        "eventCode": 2,
        "justified": 15,
        "reporterid": 17682006,
        "groupid": 11193003,
        "lesson": 7,
        "lessondate": "2013-09-09T00:00:00",
        "name": "העדרות",
        "justification": "לימודים באוניברסיטה",
        "teacherName": "שורק פיטר",
        "subjectName": "אנגלית MODULE F",
        "remarktext": ""
    },
    {
        "studentId": 316315332,
        "lessonId": 2207,
        "eventCode": 2,
        "justified": 15,
        "reporterid": 24621054,
        "groupid": 11011008,
        "lesson": 3,
        "lessondate": "2013-09-08T00:00:00",
        "name": "העדרות",
        "justification": "לימודים באוניברסיטה",
        "teacherName": "פרידמן דורית",
        "subjectName": "ספרות",
        "remarktext": ""
    },
    {
        "studentId": 316315332,
        "lessonId": 2208,
        "eventCode": 2,
        "justified": 15,
        "reporterid": 24621054,
        "groupid": 11011008,
        "lesson": 4,
        "lessondate": "2013-09-08T00:00:00",
        "name": "העדרות",
        "justification": "לימודים באוניברסיטה",
        "teacherName": "פרידמן דורית",
        "subjectName": "ספרות",
        "remarktext": ""
    },
    {
        "studentId": 316315332,
        "lessonId": 1569,
        "eventCode": 6,
        "justified": -1,
        "reporterid": 37507167,
        "groupid": 11018006,
        "lesson": 5,
        "lessondate": "2013-09-02T00:00:00",
        "name": "ללא ציוד",
        "justification": "ללא הערות",
        "teacherName": "מגל אילנית",
        "subjectName": "אזרחות",
        "remarktext": ""
    },
    {
        "studentId": 316315332,
        "lessonId": 1106,
        "eventCode": 2,
        "justified": 15,
        "reporterid": 24621054,
        "groupid": 11011008,
        "lesson": 3,
        "lessondate": "2013-09-01T00:00:00",
        "name": "העדרות",
        "justification": "לימודים באוניברסיטה",
        "teacherName": "פרידמן דורית",
        "subjectName": "ספרות",
        "remarktext": ""
    },
    {
        "studentId": 316315332,
        "lessonId": 1107,
        "eventCode": 2,
        "justified": 15,
        "reporterid": 24621054,
        "groupid": 11011008,
        "lesson": 4,
        "lessondate": "2013-09-01T00:00:00",
        "name": "העדרות",
        "justification": "לימודים באוניברסיטה",
        "teacherName": "פרידמן דורית",
        "subjectName": "ספרות",
        "remarktext": ""
    },
    {
        "studentId": 316315332,
        "lessonId": 1093,
        "eventCode": 2,
        "justified": 10,
        "reporterid": 37507167,
        "groupid": 11018006,
        "lesson": 2,
        "lessondate": "2013-08-30T00:00:00",
        "name": "העדרות",
        "justification": "יום לפני מבחן",
        "teacherName": "מגל אילנית",
        "subjectName": "אזרחות",
        "remarktext": ""
    }
]}
